azdo_pipeline/__init__.py
azdo_pipeline/__main__.py
azdo_pipeline-1.0.2.data/scripts/call_azdo_pipeline
azdo_pipeline-1.0.2.dist-info/METADATA
azdo_pipeline-1.0.2.dist-info/WHEEL
azdo_pipeline-1.0.2.dist-info/entry_points.txt
azdo_pipeline-1.0.2.dist-info/RECORD
