Metadata-Version: 2.1
Name: azdo_pipeline
Version: 1.0.2
Summary: Call Azure DevOps pipeline and optionally search output.
Home-page: https://gitlab.com/fer1035_python/modules/pypi-azdo_pipeline
License: GPL-2.0-only
Keywords: Azure,DevOps,pipelines,API,search
Author: Ahmad Ferdaus Abd Razak
Author-email: fer1035@gmail.com
Requires-Python: >=3.9,<4.0
Classifier: License :: OSI Approved :: GNU General Public License v2 (GPLv2)
Classifier: Programming Language :: Python :: 3
Classifier: Programming Language :: Python :: 3.9
Classifier: Programming Language :: Python :: 3.10
Classifier: Programming Language :: Python :: 3.11
Classifier: Programming Language :: Python :: 3.12
Project-URL: Repository, https://gitlab.com/fer1035_python/modules/pypi-azdo_pipeline
